ssl_common_utils/__init__.py
ssl_common_utils/py.typed
ssl_common_utils-0.1.0.dist-info/METADATA
ssl_common_utils-0.1.0.dist-info/WHEEL
ssl_common_utils-0.1.0.dist-info/RECORD
