Metadata-Version: 2.4
Name: ssl-common-utils
Version: 0.1.0
Summary: Add your description here
Author-email: ssl <simplystronglab@gmail.com>
Requires-Python: >=3.13
Requires-Dist: ruff>=0.11.8
